Metadata-Version: 2.1
Name: validatos
Version: 1.1
Summary: Paquete para validación de información
Home-page: https://github.com/ovillalbah/validatos
Author: Admin SpotyUN
License: UNKNOWN
Download-URL: https://github.com/ovillalbah/validatos/tallbars/1.0
Keywords: validacion,informacion
Platform: UNKNOWN
